ctp/__init__.py
ctp/_ctp.cpython-310-darwin.so
ctp/ctp.py
ctp/thostmduserapi_se.framework/Headers
ctp/thostmduserapi_se.framework/Resources
ctp/thostmduserapi_se.framework/thostmduserapi_se
ctp/thostmduserapi_se.framework/Versions/Current
ctp/thostmduserapi_se.framework/Versions/A/thostmduserapi_se
ctp/thostmduserapi_se.framework/Versions/A/Headers/ThostFtdcMdApi.h
ctp/thostmduserapi_se.framework/Versions/A/Headers/ThostFtdcUserApiDataType.h
ctp/thostmduserapi_se.framework/Versions/A/Headers/ThostFtdcUserApiStruct.h
ctp/thostmduserapi_se.framework/Versions/A/Resources/Info.plist
ctp/thostmduserapi_se.framework/Versions/A/_CodeSignature/CodeResources
ctp/thosttraderapi_se.framework/Headers
ctp/thosttraderapi_se.framework/Resources
ctp/thosttraderapi_se.framework/thosttraderapi_se
ctp/thosttraderapi_se.framework/Versions/Current
ctp/thosttraderapi_se.framework/Versions/A/thosttraderapi_se
ctp/thosttraderapi_se.framework/Versions/A/Headers/ThostFtdcTraderApi.h
ctp/thosttraderapi_se.framework/Versions/A/Headers/ThostFtdcUserApiDataType.h
ctp/thosttraderapi_se.framework/Versions/A/Headers/ThostFtdcUserApiStruct.h
ctp/thosttraderapi_se.framework/Versions/A/Resources/Info.plist
ctp/thosttraderapi_se.framework/Versions/A/_CodeSignature/CodeResources
ctp_python-6.7.7.dist-info/LICENSE
ctp_python-6.7.7.dist-info/METADATA
ctp_python-6.7.7.dist-info/WHEEL
ctp_python-6.7.7.dist-info/top_level.txt
ctp_python-6.7.7.dist-info/RECORD
